dont_fuck_with_paste/__init__.py
dont_fuck_with_paste/cli.py
dont_fuck_with_paste-0.1.7.dist-info/LICENSE
dont_fuck_with_paste-0.1.7.dist-info/METADATA
dont_fuck_with_paste-0.1.7.dist-info/WHEEL
dont_fuck_with_paste-0.1.7.dist-info/entry_points.txt
dont_fuck_with_paste-0.1.7.dist-info/RECORD
