Metadata-Version: 2.1
Name: dont-fuck-with-paste
Version: 0.1.7
Summary: Uses keyboard.write() to simulate pasting
Home-page: https://github.com/tddschn/dont-fuck-with-paste
License: MIT
Keywords: keyboard,utility,pasting,clipboard,gui,automation
Author: Teddy Xinyuan Chen
Author-email: 45612704+tddschn@users.noreply.github.com
Requires-Python: >=3.10,<4.0
Classifier: License :: OSI Approved :: MIT License
Classifier: Programming Language :: Python :: 3
Classifier: Programming Language :: Python :: 3.10
Classifier: Programming Language :: Python :: 3.11
Classifier: Programming Language :: Python :: 3.12
Classifier: Topic :: Utilities
Requires-Dist: keyboard (>=0.13.5,<0.14.0)
Requires-Dist: pyperclip (>=1.9.0,<2.0.0)
Project-URL: Bug Tracker, https://github.com/tddschn/dont-fuck-with-paste/issues
Project-URL: Repository, https://github.com/tddschn/dont-fuck-with-paste
